rlsdk_python/__init__.py
rlsdk_python/event_handling.py
rlsdk_python/events.py
rlsdk_python/frida_script.py
rlsdk_python/game_objects.py
rlsdk_python/sdk.py
rlsdk_python-0.5.0.dist-info/METADATA
rlsdk_python-0.5.0.dist-info/WHEEL
rlsdk_python-0.5.0.dist-info/RECORD
